{
	"description": "项目配置文件",
	"packOptions": {
		"ignore": []
	},
	"setting": {
		"urlCheck": false,
		"es6": true,
		"enhance": true,
		"postcss": true,
		"minified": false,
		"newFeature": true,
		"coverView": true,
		"nodeModules": true,
		"autoAudits": false,
		"showShadowRootInWxmlPanel": false,
		"scopeDataCheck": true,
		"uglifyFileName": false,
		"checkInvalidKey": true,
		"checkSiteMap": true,
		"uploadWithSourceMap": true,
		"babelSetting": {
			"ignore": [],
			"disablePlugins": [],
			"outputPath": ""
		}
	},
	"compileType": "miniprogram",
	"libVersion": "2.10.4",
	"appid": "wxfcd3e1af4fbeadfe",
	"projectname": "PopRun",
	"debugOptions": {
		"hidedInDevtools": []
	},
	"isGameTourist": false,
	"simulatorType": "wechat",
	"simulatorPluginLibVersion": {},
	"condition": {
		"search": {
			"current": -1,
			"list": []
		},
		"conversation": {
			"current": -1,
			"list": []
		},
		"plugin": {
			"current": -1,
			"list": []
		},
		"game": {
			"currentL": -1,
			"list": []
		},
		"gamePlugin": {
			"current": -1,
			"list": []
		},
		"miniprogram": {
			"current": -1,
			"list": [
				{
					"id": -1,
					"name": "动态",
					"pathName": "pages/moments/moments",
					"query": "",
					"scene": null
				},
				{
					"id": -1,
					"name": "新建分享",
					"pathName": "pages/moments/newMoment/newMoment",
					"query": "",
					"scene": null
				},
				{
					"id": 2,
					"name": "个人中心",
					"pathName": "pages/user/user",
					"query": "个人中心",
					"scene": null
				},
				{
					"id": -1,
					"name": "用户修改",
					"pathName": "pages/user/edit/edit",
					"query": "",
					"scene": null
				},
				{
					"id": -1,
					"name": "活动广场",
					"pathName": "pages/pub/pub",
					"query": "",
					"scene": null
				},
				{
					"id": -1,
					"name": "跑步教程",
					"pathName": "pages/pub/blockMore/blockmore",
					"query": "",
					"scene": null
				},
				{
					"id": -1,
					"name": "隐私设置",
					"pathName": "pages/user/privacy/privacy",
					"query": "",
					"scene": null
				},
				{
					"id": 7,
					"name": "用户个人主页",
					"pathName": "pages/user/userPage/userPage",
					"query": "rid=10",
					"scene": null
				},
				{
					"id": 8,
					"name": "消息盒子",
					"pathName": "pages/moments/messages/messages",
					"query": "rid=10&type=moment",
					"scene": null
				}
			]
		}
	}
}